{"v":"4.8.0","ip":0,"op":166,"fr":30,"w":1000,"h":1000,"nm":"s","assets":[],"layers":[{"ind":1,"ty":4,"nm":"S","sr":1,"ks":{"o":{"a":0,"k":100},"r":{"a":0,"k":0},"p":{"a":0,"k":[500.819,597.115,0]},"a":{"a":0,"k":[-819,-438.755,0]},"s":{"a":0,"k":[100,100,100]}},"shapes":[{"ty":"gr","nm":"S","it":[{"ty":"sh","nm":"P","ind":0,"ks":{"k":{"i":[[0,0]],"o":[[0,0]],"v":[[-51,115]],"c":false},"a":0}},{"ty":"st","nm":"S","lc":1,"lj":1,"ml":4,"o":{"a":0,"k":100},"w":{"a":0,"k":15},"c":{"a":0,"k":[0.137,0.137,0.137,1]}},{"ty":"tr","o":{"a":0,"k":100},"r":{"a":0,"k":0},"p":{"a":0,"k":[0,0]},"a":{"a":0,"k":[0,0]},"s":{"a":0,"k":[100,100]},"nm":"T","sk":{"a":0,"k":0},"sa":{"a":0,"k":0}}]},{"ty":"gr","nm":"G","it":[{"ty":"gr","nm":"G","it":[{"ty":"rc","nm":"R","d":1,"s":{"a":0,"k":[10.366,27.28]},"p":{"a":0,"k":[0,0]},"r":{"a":0,"k":0}},{"ty":"st","nm":"S","lc":1,"lj":1,"ml":10,"o":{"a":0,"k":100},"w":{"a":0,"k":1},"c":{"a":0,"k":[0.137,0.137,0.137,1]}},{"ty":"fl","nm":"F","c":{"a":0,"k":[0.025,0.032,0.032,1]},"o":{"a":0,"k":100},"r":1},{"ty":"tr","o":{"a":0,"k":100},"r":{"a":0,"k":0},"p":{"a":0,"k":[-775.82,-454.869]},"a":{"a":0,"k":[0,0]},"s":{"a":0,"k":[100,100]},"nm":"T","sk":{"a":0,"k":0},"sa":{"a":0,"k":0}}]},{"ty":"tr","o":{"a":1,"k":[{"i":{"x":[0.667],"y":[1]},"o":{"x":[0.333],"y":[0]},"t":28,"s":[100]},{"i":{"x":[0.667],"y":[1]},"o":{"x":[0.333],"y":[0]},"t":31,"s":[0]},{"t":35,"s":[100]}]},"r":{"a":0,"k":0},"p":{"a":0,"k":[0,0]},"a":{"a":0,"k":[0,0]},"s":{"a":0,"k":[100,100]},"nm":"T","sk":{"a":0,"k":0},"sa":{"a":0,"k":0}}]},{"ty":"gr","nm":"G","it":[{"ty":"gr","nm":"G","it":[{"ty":"rc","nm":"R","d":1,"s":{"a":0,"k":[10.366,27.28]},"p":{"a":0,"k":[0,0]},"r":{"a":0,"k":0}},{"ty":"st","nm":"S","lc":1,"lj":1,"ml":10,"o":{"a":0,"k":100},"w":{"a":0,"k":1},"c":{"a":0,"k":[0.137,0.137,0.137,1]}},{"ty":"fl","nm":"F","c":{"a":0,"k":[0.025,0.032,0.032,1]},"o":{"a":0,"k":100},"r":1},{"ty":"tr","o":{"a":0,"k":100},"r":{"a":0,"k":0},"p":{"a":0,"k":[-798.27,-454.869]},"a":{"a":0,"k":[0,0]},"s":{"a":0,"k":[100,100]},"nm":"T","sk":{"a":0,"k":0},"sa":{"a":0,"k":0}}]},{"ty":"tr","o":{"a":1,"k":[{"i":{"x":[0.667],"y":[1]},"o":{"x":[0.333],"y":[0]},"t":21,"s":[100]},{"i":{"x":[0.667],"y":[1]},"o":{"x":[0.333],"y":[0]},"t":24,"s":[0]},{"t":28,"s":[100]}]},"r":{"a":0,"k":0},"p":{"a":0,"k":[0,0]},"a":{"a":0,"k":[0,0]},"s":{"a":0,"k":[100,100]},"nm":"T","sk":{"a":0,"k":0},"sa":{"a":0,"k":0}}]},{"ty":"gr","nm":"G","it":[{"ty":"gr","nm":"G","it":[{"ty":"rc","nm":"R","d":1,"s":{"a":0,"k":[10.366,27.28]},"p":{"a":0,"k":[0,0]},"r":{"a":0,"k":0}},{"ty":"st","nm":"S","lc":1,"lj":1,"ml":10,"o":{"a":0,"k":100},"w":{"a":0,"k":1},"c":{"a":0,"k":[0.137,0.137,0.137,1]}},{"ty":"fl","nm":"F","c":{"a":0,"k":[0.025,0.032,0.032,1]},"o":{"a":0,"k":100},"r":1},{"ty":"tr","o":{"a":0,"k":100},"r":{"a":0,"k":0},"p":{"a":0,"k":[-820.719,-454.869]},"a":{"a":0,"k":[0,0]},"s":{"a":0,"k":[100,100]},"nm":"T","sk":{"a":0,"k":0},"sa":{"a":0,"k":0}}]},{"ty":"tr","o":{"a":1,"k":[{"i":{"x":[0.667],"y":[1]},"o":{"x":[0.333],"y":[0]},"t":14,"s":[100]},{"i":{"x":[0.667],"y":[1]},"o":{"x":[0.333],"y":[0]},"t":17,"s":[0]},{"t":21,"s":[100]}]},"r":{"a":0,"k":0},"p":{"a":0,"k":[0,0]},"a":{"a":0,"k":[0,0]},"s":{"a":0,"k":[100,100]},"nm":"T","sk":{"a":0,"k":0},"sa":{"a":0,"k":0}}]},{"ty":"gr","nm":"G","it":[{"ty":"gr","nm":"G","it":[{"ty":"rc","nm":"R","d":1,"s":{"a":0,"k":[10.366,27.28]},"p":{"a":0,"k":[0,0]},"r":{"a":0,"k":0}},{"ty":"st","nm":"S","lc":1,"lj":1,"ml":10,"o":{"a":0,"k":100},"w":{"a":0,"k":1},"c":{"a":0,"k":[0.137,0.137,0.137,1]}},{"ty":"fl","nm":"F","c":{"a":0,"k":[0.025,0.032,0.032,1]},"o":{"a":0,"k":100},"r":1},{"ty":"tr","o":{"a":0,"k":100},"r":{"a":0,"k":0},"p":{"a":0,"k":[-843.168,-454.869]},"a":{"a":0,"k":[0,0]},"s":{"a":0,"k":[100,100]},"nm":"T","sk":{"a":0,"k":0},"sa":{"a":0,"k":0}}]},{"ty":"tr","o":{"a":1,"k":[{"i":{"x":[0.667],"y":[1]},"o":{"x":[0.333],"y":[0]},"t":7,"s":[100]},{"i":{"x":[0.667],"y":[1]},"o":{"x":[0.333],"y":[0]},"t":10,"s":[0]},{"t":14,"s":[100]}]},"r":{"a":0,"k":0},"p":{"a":0,"k":[0,0]},"a":{"a":0,"k":[0,0]},"s":{"a":0,"k":[100,100]},"nm":"T","sk":{"a":0,"k":0},"sa":{"a":0,"k":0}}]},{"ty":"gr","nm":"G","it":[{"ty":"gr","nm":"G","it":[{"ty":"rc","nm":"R","d":1,"s":{"a":0,"k":[10.366,27.28]},"p":{"a":0,"k":[0,0]},"r":{"a":0,"k":0}},{"ty":"st","nm":"S","lc":1,"lj":1,"ml":10,"o":{"a":0,"k":100},"w":{"a":0,"k":1},"c":{"a":0,"k":[0.137,0.137,0.137,1]}},{"ty":"fl","nm":"F","c":{"a":0,"k":[0.025,0.032,0.032,1]},"o":{"a":0,"k":100},"r":1},{"ty":"tr","o":{"a":1,"k":[{"i":{"x":[0.667],"y":[1]},"o":{"x":[0.333],"y":[0]},"t":0,"s":[100]},{"i":{"x":[0.667],"y":[1]},"o":{"x":[0.333],"y":[0]},"t":3,"s":[0]},{"t":7,"s":[100]}]},"r":{"a":0,"k":0},"p":{"a":0,"k":[-865.617,-454.869]},"a":{"a":0,"k":[0,0]},"s":{"a":0,"k":[100,100]},"nm":"T","sk":{"a":0,"k":0},"sa":{"a":0,"k":0}}]},{"ty":"tr","o":{"a":0,"k":100},"r":{"a":0,"k":0},"p":{"a":0,"k":[0,0]},"a":{"a":0,"k":[0,0]},"s":{"a":0,"k":[100,100]},"nm":"T","sk":{"a":0,"k":0},"sa":{"a":0,"k":0}}]}],"ip":0,"op":166,"st":0},{"ind":2,"ty":4,"nm":"S","sr":1,"ks":{"o":{"a":0,"k":100},"r":{"a":1,"k":[{"i":{"x":[0.667],"y":[1]},"o":{"x":[0.333],"y":[0]},"t":31,"s":[0]},{"i":{"x":[0.667],"y":[1]},"o":{"x":[0.333],"y":[0]},"t":48.825,"s":[118]},{"i":{"x":[0.667],"y":[1]},"o":{"x":[0.333],"y":[0]},"t":56.575,"s":[98]},{"i":{"x":[0.667],"y":[1]},"o":{"x":[0.333],"y":[0]},"t":64.325,"s":[127]},{"i":{"x":[0.667],"y":[1]},"o":{"x":[0.333],"y":[0]},"t":72.075,"s":[57]},{"i":{"x":[0.667],"y":[1]},"o":{"x":[0.333],"y":[0]},"t":79.825,"s":[97]},{"i":{"x":[0.667],"y":[1]},"o":{"x":[0.333],"y":[0]},"t":87.575,"s":[67]},{"i":{"x":[0.667],"y":[1]},"o":{"x":[0.333],"y":[0]},"t":95.325,"s":[125]},{"i":{"x":[0.667],"y":[1]},"o":{"x":[0.333],"y":[0]},"t":103.075,"s":[114]},{"i":{"x":[0.667],"y":[1]},"o":{"x":[0.333],"y":[0]},"t":110.825,"s":[126]},{"i":{"x":[0.667],"y":[1]},"o":{"x":[0.333],"y":[0]},"t":118.575,"s":[100]},{"i":{"x":[0.667],"y":[1]},"o":{"x":[0.333],"y":[0]},"t":126.325,"s":[116]},{"i":{"x":[0.667],"y":[1]},"o":{"x":[0.333],"y":[0]},"t":134.075,"s":[74]},{"t":164,"s":[0]}]},"p":{"a":0,"k":[501,494.25,0]},"a":{"a":0,"k":[1,-1,0]},"s":{"a":0,"k":[100,100,100]}},"shapes":[{"ty":"gr","nm":"S","it":[{"ty":"sh","nm":"P","ind":0,"ks":{"k":{"i":[[0,0],[0,0]],"o":[[0,0],[0,0]],"v":[[1,-1],[-72,-47.59]],"c":false},"a":0}},{"ty":"st","nm":"S","lc":2,"lj":1,"ml":4,"o":{"a":0,"k":100},"w":{"a":0,"k":15},"c":{"a":0,"k":[0.137,0.137,0.137,1]}},{"ty":"tr","o":{"a":0,"k":100},"r":{"a":0,"k":0},"p":{"a":0,"k":[0,0]},"a":{"a":0,"k":[0,0]},"s":{"a":0,"k":[100,100]},"nm":"T","sk":{"a":0,"k":0},"sa":{"a":0,"k":0}}]}],"ip":0,"op":166,"st":0},{"ind":3,"ty":4,"nm":"L","sr":1,"ks":{"o":{"a":0,"k":100},"r":{"a":0,"k":0},"p":{"a":0,"k":[500,498,0]},"a":{"a":0,"k":[-821.021,-550.377,0]},"s":{"a":0,"k":[100,100,100]}},"shapes":[{"ty":"gr","nm":"G","it":[{"ty":"gr","nm":"G","it":[{"ty":"st","nm":"S","lc":1,"lj":1,"ml":10,"o":{"a":0,"k":100},"w":{"a":0,"k":1},"c":{"a":0,"k":[0.137,0.137,0.137,1]}},{"ty":"fl","nm":"F","c":{"a":0,"k":[0.025,0.032,0.032,1]},"o":{"a":0,"k":100},"r":1},{"ty":"tr","o":{"a":0,"k":100},"r":{"a":0,"k":0},"p":{"a":0,"k":[0,0]},"a":{"a":0,"k":[0,0]},"s":{"a":0,"k":[100,100]},"nm":"T","sk":{"a":0,"k":0},"sa":{"a":0,"k":0}}]},{"ty":"tr","o":{"a":0,"k":100},"r":{"a":0,"k":0},"p":{"a":0,"k":[0,0]},"a":{"a":0,"k":[0,0]},"s":{"a":0,"k":[100,100]},"nm":"T","sk":{"a":0,"k":0},"sa":{"a":0,"k":0}}]},{"ty":"gr","nm":"G","it":[{"ty":"gr","nm":"G","it":[{"ty":"rc","nm":"R","d":1,"s":{"a":0,"k":[32.964,10.366]},"p":{"a":0,"k":[0,0]},"r":{"a":0,"k":0}},{"ty":"st","nm":"S","lc":1,"lj":1,"ml":10,"o":{"a":0,"k":100},"w":{"a":0,"k":1},"c":{"a":0,"k":[0.137,0.137,0.137,1]}},{"ty":"fl","nm":"F","c":{"a":0,"k":[0.025,0.032,0.032,1]},"o":{"a":0,"k":100},"r":1},{"ty":"tr","o":{"a":0,"k":100},"r":{"a":0,"k":0},"p":{"a":0,"k":[-693.448,-548.377]},"a":{"a":0,"k":[0,0]},"s":{"a":0,"k":[100,100]},"nm":"T","sk":{"a":0,"k":0},"sa":{"a":0,"k":0}}]},{"ty":"tr","o":{"a":0,"k":100},"r":{"a":0,"k":0},"p":{"a":0,"k":[0,0]},"a":{"a":0,"k":[0,0]},"s":{"a":0,"k":[100,100]},"nm":"T","sk":{"a":0,"k":0},"sa":{"a":0,"k":0}}]},{"ty":"gr","nm":"G","it":[{"ty":"gr","nm":"G","it":[{"ty":"sh","nm":"P","ind":0,"ks":{"k":{"i":[[0,0],[0,0],[0,0],[0,0]],"o":[[0,0],[0,0],[0,0],[0,0]],"v":[[-712.374,-572.124],[-715.057,-582.135],[-683.216,-590.664],[-680.534,-580.653]],"c":true},"a":0}},{"ty":"st","nm":"S","lc":1,"lj":1,"ml":10,"o":{"a":0,"k":100},"w":{"a":0,"k":1},"c":{"a":0,"k":[0.137,0.137,0.137,1]}},{"ty":"fl","nm":"F","c":{"a":0,"k":[0.025,0.032,0.032,1]},"o":{"a":0,"k":100},"r":1},{"ty":"tr","o":{"a":0,"k":100},"r":{"a":0,"k":0},"p":{"a":0,"k":[0,0]},"a":{"a":0,"k":[0,0]},"s":{"a":0,"k":[100,100]},"nm":"T","sk":{"a":0,"k":0},"sa":{"a":0,"k":0}}]},{"ty":"tr","o":{"a":0,"k":100},"r":{"a":0,"k":0},"p":{"a":0,"k":[0,0]},"a":{"a":0,"k":[0,0]},"s":{"a":0,"k":[100,100]},"nm":"T","sk":{"a":0,"k":0},"sa":{"a":0,"k":0}}]},{"ty":"gr","nm":"G","it":[{"ty":"gr","nm":"G","it":[{"ty":"sh","nm":"P","ind":0,"ks":{"k":{"i":[[0,0],[0,0],[0,0],[0,0]],"o":[[0,0],[0,0],[0,0],[0,0]],"v":[[-722.221,-599.435],[-727.404,-608.414],[-698.858,-624.893],[-693.675,-615.914]],"c":true},"a":0}},{"ty":"st","nm":"S","lc":1,"lj":1,"ml":10,"o":{"a":0,"k":100},"w":{"a":0,"k":1},"c":{"a":0,"k":[0.137,0.137,0.137,1]}},{"ty":"fl","nm":"F","c":{"a":0,"k":[0.025,0.032,0.032,1]},"o":{"a":0,"k":100},"r":1},{"ty":"tr","o":{"a":0,"k":100},"r":{"a":0,"k":0},"p":{"a":0,"k":[0,0]},"a":{"a":0,"k":[0,0]},"s":{"a":0,"k":[100,100]},"nm":"T","sk":{"a":0,"k":0},"sa":{"a":0,"k":0}}]},{"ty":"tr","o":{"a":0,"k":100},"r":{"a":0,"k":0},"p":{"a":0,"k":[0,0]},"a":{"a":0,"k":[0,0]},"s":{"a":0,"k":[100,100]},"nm":"T","sk":{"a":0,"k":0},"sa":{"a":0,"k":0}}]},{"ty":"gr","nm":"G","it":[{"ty":"gr","nm":"G","it":[{"ty":"sh","nm":"P","ind":0,"ks":{"k":{"i":[[0,0],[0,0],[0,0],[0,0]],"o":[[0,0],[0,0],[0,0],[0,0]],"v":[[-738.804,-623.264],[-746.133,-630.593],[-722.823,-653.905],[-715.495,-646.576]],"c":true},"a":0}},{"ty":"st","nm":"S","lc":1,"lj":1,"ml":10,"o":{"a":0,"k":100},"w":{"a":0,"k":1},"c":{"a":0,"k":[0.137,0.137,0.137,1]}},{"ty":"fl","nm":"F","c":{"a":0,"k":[0.025,0.032,0.032,1]},"o":{"a":0,"k":100},"r":1},{"ty":"tr","o":{"a":0,"k":100},"r":{"a":0,"k":0},"p":{"a":0,"k":[0,0]},"a":{"a":0,"k":[0,0]},"s":{"a":0,"k":[100,100]},"nm":"T","sk":{"a":0,"k":0},"sa":{"a":0,"k":0}}]},{"ty":"tr","o":{"a":0,"k":100},"r":{"a":0,"k":0},"p":{"a":0,"k":[0,0]},"a":{"a":0,"k":[0,0]},"s":{"a":0,"k":[100,100]},"nm":"T","sk":{"a":0,"k":0},"sa":{"a":0,"k":0}}]},{"ty":"gr","nm":"G","it":[{"ty":"gr","nm":"G","it":[{"ty":"sh","nm":"P","ind":0,"ks":{"k":{"i":[[0,0],[0,0],[0,0],[0,0]],"o":[[0,0],[0,0],[0,0],[0,0]],"v":[[-760.985,-641.995],[-769.964,-647.178],[-753.482,-675.724],[-744.503,-670.541]],"c":true},"a":0}},{"ty":"st","nm":"S","lc":1,"lj":1,"ml":10,"o":{"a":0,"k":100},"w":{"a":0,"k":1},"c":{"a":0,"k":[0.137,0.137,0.137,1]}},{"ty":"fl","nm":"F","c":{"a":0,"k":[0.025,0.032,0.032,1]},"o":{"a":0,"k":100},"r":1},{"ty":"tr","o":{"a":0,"k":100},"r":{"a":0,"k":0},"p":{"a":0,"k":[0,0]},"a":{"a":0,"k":[0,0]},"s":{"a":0,"k":[100,100]},"nm":"T","sk":{"a":0,"k":0},"sa":{"a":0,"k":0}}]},{"ty":"tr","o":{"a":0,"k":100},"r":{"a":0,"k":0},"p":{"a":0,"k":[0,0]},"a":{"a":0,"k":[0,0]},"s":{"a":0,"k":[100,100]},"nm":"T","sk":{"a":0,"k":0},"sa":{"a":0,"k":0}}]},{"ty":"gr","nm":"G","it":[{"ty":"gr","nm":"G","it":[{"ty":"sh","nm":"P","ind":0,"ks":{"k":{"i":[[0,0],[0,0],[0,0],[0,0]],"o":[[0,0],[0,0],[0,0],[0,0]],"v":[[-787.264,-654.34],[-797.275,-657.023],[-788.742,-688.863],[-778.73,-686.18]],"c":true},"a":0}},{"ty":"st","nm":"S","lc":1,"lj":1,"ml":10,"o":{"a":0,"k":100},"w":{"a":0,"k":1},"c":{"a":0,"k":[0.137,0.137,0.137,1]}},{"ty":"fl","nm":"F","c":{"a":0,"k":[0.025,0.032,0.032,1]},"o":{"a":0,"k":100},"r":1},{"ty":"tr","o":{"a":0,"k":100},"r":{"a":0,"k":0},"p":{"a":0,"k":[0,0]},"a":{"a":0,"k":[0,0]},"s":{"a":0,"k":[100,100]},"nm":"T","sk":{"a":0,"k":0},"sa":{"a":0,"k":0}}]},{"ty":"tr","o":{"a":0,"k":100},"r":{"a":0,"k":0},"p":{"a":0,"k":[0,0]},"a":{"a":0,"k":[0,0]},"s":{"a":0,"k":[100,100]},"nm":"T","sk":{"a":0,"k":0},"sa":{"a":0,"k":0}}]},{"ty":"gr","nm":"G","it":[{"ty":"gr","nm":"G","it":[{"ty":"rc","nm":"R","d":1,"s":{"a":0,"k":[10.366,32.964]},"p":{"a":0,"k":[0,0]},"r":{"a":0,"k":0}},{"ty":"st","nm":"S","lc":1,"lj":1,"ml":10,"o":{"a":0,"k":100},"w":{"a":0,"k":1},"c":{"a":0,"k":[0.137,0.137,0.137,1]}},{"ty":"fl","nm":"F","c":{"a":0,"k":[0.025,0.032,0.032,1]},"o":{"a":0,"k":100},"r":1},{"ty":"tr","o":{"a":0,"k":100},"r":{"a":0,"k":0},"p":{"a":0,"k":[-821.022,-675.949]},"a":{"a":0,"k":[0,0]},"s":{"a":0,"k":[100,100]},"nm":"T","sk":{"a":0,"k":0},"sa":{"a":0,"k":0}}]},{"ty":"tr","o":{"a":0,"k":100},"r":{"a":0,"k":0},"p":{"a":0,"k":[0,0]},"a":{"a":0,"k":[0,0]},"s":{"a":0,"k":[100,100]},"nm":"T","sk":{"a":0,"k":0},"sa":{"a":0,"k":0}}]},{"ty":"gr","nm":"G","it":[{"ty":"gr","nm":"G","it":[{"ty":"sh","nm":"P","ind":0,"ks":{"k":{"i":[[0,0],[0,0],[0,0],[0,0]],"o":[[0,0],[0,0],[0,0],[0,0]],"v":[[-854.779,-654.34],[-863.312,-686.18],[-853.301,-688.863],[-844.767,-657.023]],"c":true},"a":0}},{"ty":"st","nm":"S","lc":1,"lj":1,"ml":10,"o":{"a":0,"k":100},"w":{"a":0,"k":1},"c":{"a":0,"k":[0.137,0.137,0.137,1]}},{"ty":"fl","nm":"F","c":{"a":0,"k":[0.025,0.032,0.032,1]},"o":{"a":0,"k":100},"r":1},{"ty":"tr","o":{"a":0,"k":100},"r":{"a":0,"k":0},"p":{"a":0,"k":[0,0]},"a":{"a":0,"k":[0,0]},"s":{"a":0,"k":[100,100]},"nm":"T","sk":{"a":0,"k":0},"sa":{"a":0,"k":0}}]},{"ty":"tr","o":{"a":0,"k":100},"r":{"a":0,"k":0},"p":{"a":0,"k":[0,0]},"a":{"a":0,"k":[0,0]},"s":{"a":0,"k":[100,100]},"nm":"T","sk":{"a":0,"k":0},"sa":{"a":0,"k":0}}]},{"ty":"gr","nm":"G","it":[{"ty":"gr","nm":"G","it":[{"ty":"sh","nm":"P","ind":0,"ks":{"k":{"i":[[0,0],[0,0],[0,0],[0,0]],"o":[[0,0],[0,0],[0,0],[0,0]],"v":[[-881.057,-641.995],[-897.539,-670.541],[-888.56,-675.724],[-872.078,-647.178]],"c":true},"a":0}},{"ty":"st","nm":"S","lc":1,"lj":1,"ml":10,"o":{"a":0,"k":100},"w":{"a":0,"k":1},"c":{"a":0,"k":[0.137,0.137,0.137,1]}},{"ty":"fl","nm":"F","c":{"a":0,"k":[0.025,0.032,0.032,1]},"o":{"a":0,"k":100},"r":1},{"ty":"tr","o":{"a":0,"k":100},"r":{"a":0,"k":0},"p":{"a":0,"k":[0,0]},"a":{"a":0,"k":[0,0]},"s":{"a":0,"k":[100,100]},"nm":"T","sk":{"a":0,"k":0},"sa":{"a":0,"k":0}}]},{"ty":"tr","o":{"a":0,"k":100},"r":{"a":0,"k":0},"p":{"a":0,"k":[0,0]},"a":{"a":0,"k":[0,0]},"s":{"a":0,"k":[100,100]},"nm":"T","sk":{"a":0,"k":0},"sa":{"a":0,"k":0}}]},{"ty":"gr","nm":"G","it":[{"ty":"gr","nm":"G","it":[{"ty":"sh","nm":"P","ind":0,"ks":{"k":{"i":[[0,0],[0,0],[0,0],[0,0]],"o":[[0,0],[0,0],[0,0],[0,0]],"v":[[-903.238,-623.264],[-926.547,-646.576],[-919.219,-653.905],[-895.909,-630.593]],"c":true},"a":0}},{"ty":"st","nm":"S","lc":1,"lj":1,"ml":10,"o":{"a":0,"k":100},"w":{"a":0,"k":1},"c":{"a":0,"k":[0.137,0.137,0.137,1]}},{"ty":"fl","nm":"F","c":{"a":0,"k":[0.025,0.032,0.032,1]},"o":{"a":0,"k":100},"r":1},{"ty":"tr","o":{"a":0,"k":100},"r":{"a":0,"k":0},"p":{"a":0,"k":[0,0]},"a":{"a":0,"k":[0,0]},"s":{"a":0,"k":[100,100]},"nm":"T","sk":{"a":0,"k":0},"sa":{"a":0,"k":0}}]},{"ty":"tr","o":{"a":0,"k":100},"r":{"a":0,"k":0},"p":{"a":0,"k":[0,0]},"a":{"a":0,"k":[0,0]},"s":{"a":0,"k":[100,100]},"nm":"T","sk":{"a":0,"k":0},"sa":{"a":0,"k":0}}]},{"ty":"gr","nm":"G","it":[{"ty":"gr","nm":"G","it":[{"ty":"sh","nm":"P","ind":0,"ks":{"k":{"i":[[0,0],[0,0],[0,0],[0,0]],"o":[[0,0],[0,0],[0,0],[0,0]],"v":[[-919.821,-599.435],[-948.367,-615.914],[-943.184,-624.893],[-914.638,-608.414]],"c":true},"a":0}},{"ty":"st","nm":"S","lc":1,"lj":1,"ml":10,"o":{"a":0,"k":100},"w":{"a":0,"k":1},"c":{"a":0,"k":[0.137,0.137,0.137,1]}},{"ty":"fl","nm":"F","c":{"a":0,"k":[0.025,0.032,0.032,1]},"o":{"a":0,"k":100},"r":1},{"ty":"tr","o":{"a":0,"k":100},"r":{"a":0,"k":0},"p":{"a":0,"k":[0,0]},"a":{"a":0,"k":[0,0]},"s":{"a":0,"k":[100,100]},"nm":"T","sk":{"a":0,"k":0},"sa":{"a":0,"k":0}}]},{"ty":"tr","o":{"a":0,"k":100},"r":{"a":0,"k":0},"p":{"a":0,"k":[0,0]},"a":{"a":0,"k":[0,0]},"s":{"a":0,"k":[100,100]},"nm":"T","sk":{"a":0,"k":0},"sa":{"a":0,"k":0}}]},{"ty":"gr","nm":"G","it":[{"ty":"gr","nm":"G","it":[{"ty":"sh","nm":"P","ind":0,"ks":{"k":{"i":[[0,0],[0,0],[0,0],[0,0]],"o":[[0,0],[0,0],[0,0],[0,0]],"v":[[-929.668,-572.124],[-961.508,-580.653],[-958.826,-590.664],[-926.985,-582.135]],"c":true},"a":0}},{"ty":"st","nm":"S","lc":1,"lj":1,"ml":10,"o":{"a":0,"k":100},"w":{"a":0,"k":1},"c":{"a":0,"k":[0.137,0.137,0.137,1]}},{"ty":"fl","nm":"F","c":{"a":0,"k":[0.025,0.032,0.032,1]},"o":{"a":0,"k":100},"r":1},{"ty":"tr","o":{"a":0,"k":100},"r":{"a":0,"k":0},"p":{"a":0,"k":[0,0]},"a":{"a":0,"k":[0,0]},"s":{"a":0,"k":[100,100]},"nm":"T","sk":{"a":0,"k":0},"sa":{"a":0,"k":0}}]},{"ty":"tr","o":{"a":0,"k":100},"r":{"a":0,"k":0},"p":{"a":0,"k":[0,0]},"a":{"a":0,"k":[0,0]},"s":{"a":0,"k":[100,100]},"nm":"T","sk":{"a":0,"k":0},"sa":{"a":0,"k":0}}]},{"ty":"gr","nm":"G","it":[{"ty":"gr","nm":"G","it":[{"ty":"rc","nm":"R","d":1,"s":{"a":0,"k":[32.964,10.366]},"p":{"a":0,"k":[0,0]},"r":{"a":0,"k":0}},{"ty":"st","nm":"S","lc":1,"lj":1,"ml":10,"o":{"a":0,"k":100},"w":{"a":0,"k":1},"c":{"a":0,"k":[0.137,0.137,0.137,1]}},{"ty":"fl","nm":"F","c":{"a":0,"k":[0.025,0.032,0.032,1]},"o":{"a":0,"k":100},"r":1},{"ty":"tr","o":{"a":0,"k":100},"r":{"a":0,"k":0},"p":{"a":0,"k":[-948.595,-548.377]},"a":{"a":0,"k":[0,0]},"s":{"a":0,"k":[100,100]},"nm":"T","sk":{"a":0,"k":0},"sa":{"a":0,"k":0}}]},{"ty":"tr","o":{"a":0,"k":100},"r":{"a":0,"k":0},"p":{"a":0,"k":[0,0]},"a":{"a":0,"k":[0,0]},"s":{"a":0,"k":[100,100]},"nm":"T","sk":{"a":0,"k":0},"sa":{"a":0,"k":0}}]},{"ty":"gr","nm":"G","it":[{"ty":"gr","nm":"G","it":[{"ty":"sh","nm":"P","ind":0,"ks":{"k":{"i":[[0,0],[0,0],[0,0],[0,0],[0,0],[0,0],[0,0],[0,15.726],[-82.289,0],[0,-82.291],[4.872,-14.956]],"o":[[0,0],[0,0],[0,0],[0,0],[0,0],[0,0],[-4.872,-14.956],[0,-82.291],[82.291,0],[0,15.726],[0,0]],"v":[[-680.288,-498.563],[-743.835,-498.563],[-755.322,-553.119],[-886.721,-553.119],[-898.207,-498.563],[-961.754,-498.563],[-962.918,-502.142],[-970.259,-548.377],[-821.022,-697.614],[-671.783,-548.377],[-679.124,-502.142]],"c":true},"a":0}},{"ty":"st","nm":"S","lc":2,"lj":1,"ml":10,"o":{"a":0,"k":100},"w":{"a":0,"k":15},"c":{"a":0,"k":[0.137,0.137,0.137,1]}},{"ty":"tr","o":{"a":0,"k":100},"r":{"a":0,"k":0},"p":{"a":0,"k":[0,0]},"a":{"a":0,"k":[0,0]},"s":{"a":0,"k":[100,100]},"nm":"T","sk":{"a":0,"k":0},"sa":{"a":0,"k":0}}]},{"ty":"tr","o":{"a":0,"k":100},"r":{"a":0,"k":0},"p":{"a":0,"k":[0,0]},"a":{"a":0,"k":[0,0]},"s":{"a":0,"k":[100,100]},"nm":"T","sk":{"a":0,"k":0},"sa":{"a":0,"k":0}}]},{"ty":"gr","nm":"G","it":[{"ty":"gr","nm":"G","it":[{"ty":"sh","nm":"P","ind":0,"ks":{"k":{"i":[[97.334,0],[0,97.334],[-97.331,0],[0,-97.333]],"o":[[-97.331,0],[0,-97.333],[97.334,0],[0,97.334]],"v":[[-821.022,-371.86],[-997.54,-548.377],[-821.022,-724.894],[-644.503,-548.377]],"c":true},"a":0}},{"ty":"st","nm":"S","lc":2,"lj":1,"ml":10,"o":{"a":0,"k":100},"w":{"a":0,"k":15},"c":{"a":0,"k":[0.137,0.137,0.137,1]}},{"ty":"tr","o":{"a":0,"k":100},"r":{"a":0,"k":0},"p":{"a":0,"k":[0,0]},"a":{"a":0,"k":[0,0]},"s":{"a":0,"k":[100,100]},"nm":"T","sk":{"a":0,"k":0},"sa":{"a":0,"k":0}}]},{"ty":"tr","o":{"a":0,"k":100},"r":{"a":0,"k":0},"p":{"a":0,"k":[0,-2]},"a":{"a":0,"k":[0,0]},"s":{"a":0,"k":[100,100]},"nm":"T","sk":{"a":0,"k":0},"sa":{"a":0,"k":0}}]}],"ip":0,"op":166,"st":0}],"markers":[]}